nia/__init__.py
nia/nia.py
nia/algorithms/__init__.py
nia/algorithms/abc.py
nia/algorithms/ga.py
nia/algorithms/pso.py
nia/crossovers/__init__.py
nia/crossovers/crossover.py
nia/crossovers/k_point.py
nia/crossovers/random_sbx.py
nia/crossovers/sbx.py
nia/mutations/__init__.py
nia/mutations/mutation.py
nia/mutations/uniform.py
nia/selections/__init__.py
nia/selections/rank.py
nia/selections/selection.py
nia/selections/tournament.py
nia-0.0.2.dist-info/LICENSE
nia-0.0.2.dist-info/METADATA
nia-0.0.2.dist-info/WHEEL
nia-0.0.2.dist-info/top_level.txt
nia-0.0.2.dist-info/RECORD
