Metadata-Version: 2.1
Name: nia
Version: 0.0.2
Summary: Nature Inspired Optimization Algorithms
Home-page: https://github.com/salar-shdk/nia
Author: salar-shdk
Author-email: amir.shdk@yahoo.com
License: UNKNOWN
Project-URL: Bug Tracker, https://github.com/salar-shdk/nia/issues
Platform: UNKNOWN
Classifier: Programming Language :: Python :: 3
Classifier: License :: OSI Approved :: MIT License
Classifier: Operating System :: OS Independent
Requires-Python: >=3.6
License-File: LICENSE
